{"data_mtime": 1685507992, "dep_lines": [11, 12, 13, 48, 56, 57, 58, 59, 60, 1, 1, 1, 1, 1, 1, 1, 1, 1, 1, 1, 1, 1, 1, 1], "dep_prios": [5, 5, 5, 5, 5, 5, 5, 5, 5, 5, 20, 20, 20, 20, 20, 20, 20, 20, 20, 20, 20, 20, 20, 30], "dependencies": ["hypothesis.strategies._internal", "hypothesis.strategies._internal.collections", "hypothesis.strategies._internal.core", "hypothesis.strategies._internal.datetime", "hypothesis.strategies._internal.ipaddress", "hypothesis.strategies._internal.misc", "hypothesis.strategies._internal.numbers", "hypothesis.strategies._internal.strategies", "hypothesis.strategies._internal.utils", "builtins", "types", "os", "warnings", "typing", "sys", "itertools", "re", "string", "collections", "html", "copy", "pprint", "traceback", "abc"], "hash": "9d13a8abac0b3261825b28590acad607581cbcc84898d3bec23b002a5679e962", "id": "hypothesis.strategies", "ignore_all": true, "interface_hash": "88771dc1941e85f240040998a11c151ac2a356e2992b1464bbebdd10ee697213", "mtime": 1654895402, "options": {"allow_redefinition": false, "allow_untyped_globals": false, "always_false": [], "always_true": [], "bazel": false, "check_untyped_defs": false, "disallow_any_decorated": false, "disallow_any_explicit": false, "disallow_any_expr": false, "disallow_any_generics": false, "disallow_any_unimported": false, "disallow_incomplete_defs": false, "disallow_subclassing_any": false, "disallow_untyped_calls": false, "disallow_untyped_decorators": false, "disallow_untyped_defs": false, "follow_imports": "silent", "follow_imports_for_stubs": false, "ignore_errors": false, "ignore_missing_imports": true, "implicit_reexport": true, "local_partial_types": false, "mypyc": false, "no_implicit_optional": false, "platform": "linux", "plugins": [], "show_none_errors": true, "strict_concatenate": false, "strict_equality": false, "strict_optional": true, "strict_optional_whitelist": null, "warn_no_return": true, "warn_return_any": false, "warn_unreachable": false, "warn_unused_ignores": false}, "path": "/cellar/users/dlaub/miniconda3/envs/drugcell_transfer/lib/python3.9/site-packages/hypothesis/strategies/__init__.py", "plugin_data": null, "size": 3278, "suppressed": [], "version_id": "0.961"}