{".class": "MypyFile", "_fullname": "polars.config", "future_import_flags": ["annotations"], "is_partial_stub_package": false, "is_stub": false, "names": {".class": "SymbolTable", "Config": {".class": "SymbolTableNode", "kind": "Gdef", "node": {".class": "TypeInfo", "_promote": null, "abstract_attributes": [], "bases": ["builtins.object"], "declared_metaclass": null, "defn": {".class": "ClassDef", "fullname": "polars.config.Config", "name": "Config", "type_vars": []}, "deletable_attributes": [], "flags": [], "fullname": "polars.config.Config", "has_param_spec_type": false, "metaclass_type": null, "metadata": {}, "module_name": "polars.config", "mro": ["polars.config.Config", "builtins.object"], "names": {".class": "SymbolTable", "__enter__": {".class": "SymbolTableNode", "kind": "Mdef", "node": {".class": "FuncDef", "arg_kinds": [0], "arg_names": [null], "flags": [], "fullname": "polars.config.Config.__enter__", "name": "__enter__", "type": {".class": "CallableType", "arg_kinds": [0], "arg_names": [null], "arg_types": ["polars.config.Config"], "bound_args": [], "def_extras": {"first_arg": "self"}, "fallback": "builtins.function", "from_concatenate": false, "implicit": false, "is_ellipsis_args": false, "name": "__enter__ of Config", "ret_type": "polars.config.Config", "type_guard": null, "variables": []}}}, "__exit__": {".class": "SymbolTableNode", "kind": "Mdef", "node": {".class": "FuncDef", "arg_kinds": [0, 0, 0, 0], "arg_names": [null, null, null, null], "flags": [], "fullname": "polars.config.Config.__exit__", "name": "__exit__", "type": {".class": "CallableType", "arg_kinds": [0, 0, 0, 0], "arg_names": [null, null, null, null], "arg_types": ["polars.config.Config", {".class": "UnionType", "items": [{".class": "TypeType", "item": "builtins.BaseException"}, {".class": "NoneType"}]}, {".class": "UnionType", "items": ["builtins.BaseException", {".class": "NoneType"}]}, {".class": "UnionType", "items": ["types.TracebackType", {".class": "NoneType"}]}], "bound_args": [], "def_extras": {"first_arg": "self"}, "fallback": "builtins.function", "from_concatenate": false, "implicit": false, "is_ellipsis_args": false, "name": "__exit__ of Config", "ret_type": {".class": "NoneType"}, "type_guard": null, "variables": []}}}, "_original_state": {".class": "SymbolTableNode", "implicit": true, "kind": "Mdef", "node": {".class": "Var", "flags": [], "fullname": "polars.config.Config._original_state", "name": "_original_state", "type": "builtins.str"}}, "activate_decimals": {".class": "SymbolTableNode", "kind": "Mdef", "node": {".class": "Decorator", "func": {".class": "FuncDef", "arg_kinds": [0], "arg_names": ["cls"], "flags": ["is_class", "is_decorated"], "fullname": "polars.config.Config.activate_decimals", "name": "activate_decimals", "type": {".class": "CallableType", "arg_kinds": [0], "arg_names": ["cls"], "arg_types": [{".class": "TypeType", "item": "polars.config.Config"}], "bound_args": [], "def_extras": {"first_arg": "cls"}, "fallback": "builtins.function", "from_concatenate": false, "implicit": false, "is_ellipsis_args": false, "name": "activate_decimals of Config", "ret_type": {".class": "TypeType", "item": "polars.config.Config"}, "type_guard": null, "variables": []}}, "is_overload": false, "var": {".class": "Var", "flags": ["is_initialized_in_class", "is_classmethod", "is_ready"], "fullname": null, "name": "activate_decimals", "type": {".class": "CallableType", "arg_kinds": [0], "arg_names": ["cls"], "arg_types": [{".class": "TypeType", "item": "polars.config.Config"}], "bound_args": [], "def_extras": {"first_arg": "cls"}, "fallback": "builtins.function", "from_concatenate": false, "implicit": false, "is_ellipsis_args": false, "name": "activate_decimals of Config", "ret_type": {".class": "TypeType", "item": "polars.config.Config"}, "type_guard": null, "variables": []}}}}, "load": {".class": "SymbolTableNode", "kind": "Mdef", "node": {".class": "Decorator", "func": {".class": "FuncDef", "arg_kinds": [0, 0], "arg_names": ["cls", "cfg"], "flags": ["is_class", "is_decorated"], "fullname": "polars.config.Config.load", "name": "load", "type": {".class": "CallableType", "arg_kinds": [0, 0], "arg_names": ["cls", "cfg"], "arg_types": [{".class": "TypeType", "item": "polars.config.Config"}, "builtins.str"], "bound_args": [], "def_extras": {"first_arg": "cls"}, "fallback": "builtins.function", "from_concatenate": false, "implicit": false, "is_ellipsis_args": false, "name": "load of Config", "ret_type": {".class": "TypeType", "item": "polars.config.Config"}, "type_guard": null, "variables": []}}, "is_overload": false, "var": {".class": "Var", "flags": ["is_initialized_in_class", "is_classmethod", "is_ready"], "fullname": null, "name": "load", "type": {".class": "CallableType", "arg_kinds": [0, 0], "arg_names": ["cls", "cfg"], "arg_types": [{".class": "TypeType", "item": "polars.config.Config"}, "builtins.str"], "bound_args": [], "def_extras": {"first_arg": "cls"}, "fallback": "builtins.function", "from_concatenate": false, "implicit": false, "is_ellipsis_args": false, "name": "load of Config", "ret_type": {".class": "TypeType", "item": "polars.config.Config"}, "type_guard": null, "variables": []}}}}, "restore_defaults": {".class": "SymbolTableNode", "kind": "Mdef", "node": {".class": "Decorator", "func": {".class": "FuncDef", "arg_kinds": [0], "arg_names": ["cls"], "flags": ["is_class", "is_decorated"], "fullname": "polars.config.Config.restore_defaults", "name": "restore_defaults", "type": {".class": "CallableType", "arg_kinds": [0], "arg_names": ["cls"], "arg_types": [{".class": "TypeType", "item": "polars.config.Config"}], "bound_args": [], "def_extras": {"first_arg": "cls"}, "fallback": "builtins.function", "from_concatenate": false, "implicit": false, "is_ellipsis_args": false, "name": "restore_defaults of Config", "ret_type": {".class": "TypeType", "item": "polars.config.Config"}, "type_guard": null, "variables": []}}, "is_overload": false, "var": {".class": "Var", "flags": ["is_initialized_in_class", "is_classmethod", "is_ready"], "fullname": null, "name": "restore_defaults", "type": {".class": "CallableType", "arg_kinds": [0], "arg_names": ["cls"], "arg_types": [{".class": "TypeType", "item": "polars.config.Config"}], "bound_args": [], "def_extras": {"first_arg": "cls"}, "fallback": "builtins.function", "from_concatenate": false, "implicit": false, "is_ellipsis_args": false, "name": "restore_defaults of Config", "ret_type": {".class": "TypeType", "item": "polars.config.Config"}, "type_guard": null, "variables": []}}}}, "save": {".class": "SymbolTableNode", "kind": "Mdef", "node": {".class": "Decorator", "func": {".class": "FuncDef", "arg_kinds": [0], "arg_names": ["cls"], "flags": ["is_class", "is_decorated"], "fullname": "polars.config.Config.save", "name": "save", "type": {".class": "CallableType", "arg_kinds": [0], "arg_names": ["cls"], "arg_types": [{".class": "TypeType", "item": "polars.config.Config"}], "bound_args": [], "def_extras": {"first_arg": "cls"}, "fallback": "builtins.function", "from_concatenate": false, "implicit": false, "is_ellipsis_args": false, "name": "save of Config", "ret_type": "builtins.str", "type_guard": null, "variables": []}}, "is_overload": false, "var": {".class": "Var", "flags": ["is_initialized_in_class", "is_classmethod", "is_ready"], "fullname": null, "name": "save", "type": {".class": "CallableType", "arg_kinds": [0], "arg_names": ["cls"], "arg_types": [{".class": "TypeType", "item": "polars.config.Config"}], "bound_args": [], "def_extras": {"first_arg": "cls"}, "fallback": "builtins.function", "from_concatenate": false, "implicit": false, "is_ellipsis_args": false, "name": "save of Config", "ret_type": "builtins.str", "type_guard": null, "variables": []}}}}, "set_ascii_tables": {".class": "SymbolTableNode", "kind": "Mdef", "node": {".class": "Decorator", "func": {".class": "FuncDef", "arg_kinds": [0, 1], "arg_names": ["cls", "active"], "flags": ["is_class", "is_decorated"], "fullname": "polars.config.Config.set_ascii_tables", "name": "set_ascii_tables", "type": {".class": "CallableType", "arg_kinds": [0, 1], "arg_names": ["cls", "active"], "arg_types": [{".class": "TypeType", "item": "polars.config.Config"}, "builtins.bool"], "bound_args": [], "def_extras": {"first_arg": "cls"}, "fallback": "builtins.function", "from_concatenate": false, "implicit": false, "is_ellipsis_args": false, "name": "set_ascii_tables of Config", "ret_type": {".class": "TypeType", "item": "polars.config.Config"}, "type_guard": null, "variables": []}}, "is_overload": false, "var": {".class": "Var", "flags": ["is_initialized_in_class", "is_classmethod", "is_ready"], "fullname": null, "name": "set_ascii_tables", "type": {".class": "CallableType", "arg_kinds": [0, 1], "arg_names": ["cls", "active"], "arg_types": [{".class": "TypeType", "item": "polars.config.Config"}, "builtins.bool"], "bound_args": [], "def_extras": {"first_arg": "cls"}, "fallback": "builtins.function", "from_concatenate": false, "implicit": false, "is_ellipsis_args": false, "name": "set_ascii_tables of Config", "ret_type": {".class": "TypeType", "item": "polars.config.Config"}, "type_guard": null, "variables": []}}}}, "set_auto_structify": {".class": "SymbolTableNode", "kind": "Mdef", "node": {".class": "Decorator", "func": {".class": "FuncDef", "arg_kinds": [0, 1], "arg_names": ["cls", "active"], "flags": ["is_class", "is_decorated"], "fullname": "polars.config.Config.set_auto_structify", "name": "set_auto_structify", "type": {".class": "CallableType", "arg_kinds": [0, 1], "arg_names": ["cls", "active"], "arg_types": [{".class": "TypeType", "item": "polars.config.Config"}, "builtins.bool"], "bound_args": [], "def_extras": {"first_arg": "cls"}, "fallback": "builtins.function", "from_concatenate": false, "implicit": false, "is_ellipsis_args": false, "name": "set_auto_structify of Config", "ret_type": {".class": "TypeType", "item": "polars.config.Config"}, "type_guard": null, "variables": []}}, "is_overload": false, "var": {".class": "Var", "flags": ["is_initialized_in_class", "is_classmethod", "is_ready"], "fullname": null, "name": "set_auto_structify", "type": {".class": "CallableType", "arg_kinds": [0, 1], "arg_names": ["cls", "active"], "arg_types": [{".class": "TypeType", "item": "polars.config.Config"}, "builtins.bool"], "bound_args": [], "def_extras": {"first_arg": "cls"}, "fallback": "builtins.function", "from_concatenate": false, "implicit": false, "is_ellipsis_args": false, "name": "set_auto_structify of Config", "ret_type": {".class": "TypeType", "item": "polars.config.Config"}, "type_guard": null, "variables": []}}}}, "set_fmt_float": {".class": "SymbolTableNode", "kind": "Mdef", "node": {".class": "Decorator", "func": {".class": "FuncDef", "arg_kinds": [0, 1], "arg_names": ["cls", "fmt"], "flags": ["is_class", "is_decorated"], "fullname": "polars.config.Config.set_fmt_float", "name": "set_fmt_float", "type": {".class": "CallableType", "arg_kinds": [0, 1], "arg_names": ["cls", "fmt"], "arg_types": [{".class": "TypeType", "item": "polars.config.Config"}, {".class": "TypeAliasType", "args": [], "type_ref": "polars.type_aliases.FloatFmt"}], "bound_args": [], "def_extras": {"first_arg": "cls"}, "fallback": "builtins.function", "from_concatenate": false, "implicit": false, "is_ellipsis_args": false, "name": "set_fmt_float of Config", "ret_type": {".class": "TypeType", "item": "polars.config.Config"}, "type_guard": null, "variables": []}}, "is_overload": false, "var": {".class": "Var", "flags": ["is_initialized_in_class", "is_classmethod", "is_ready"], "fullname": null, "name": "set_fmt_float", "type": {".class": "CallableType", "arg_kinds": [0, 1], "arg_names": ["cls", "fmt"], "arg_types": [{".class": "TypeType", "item": "polars.config.Config"}, {".class": "TypeAliasType", "args": [], "type_ref": "polars.type_aliases.FloatFmt"}], "bound_args": [], "def_extras": {"first_arg": "cls"}, "fallback": "builtins.function", "from_concatenate": false, "implicit": false, "is_ellipsis_args": false, "name": "set_fmt_float of Config", "ret_type": {".class": "TypeType", "item": "polars.config.Config"}, "type_guard": null, "variables": []}}}}, "set_fmt_str_lengths": {".class": "SymbolTableNode", "kind": "Mdef", "node": {".class": "Decorator", "func": {".class": "FuncDef", "arg_kinds": [0, 0], "arg_names": ["cls", "n"], "flags": ["is_class", "is_decorated"], "fullname": "polars.config.Config.set_fmt_str_lengths", "name": "set_fmt_str_lengths", "type": {".class": "CallableType", "arg_kinds": [0, 0], "arg_names": ["cls", "n"], "arg_types": [{".class": "TypeType", "item": "polars.config.Config"}, "builtins.int"], "bound_args": [], "def_extras": {"first_arg": "cls"}, "fallback": "builtins.function", "from_concatenate": false, "implicit": false, "is_ellipsis_args": false, "name": "set_fmt_str_lengths of Config", "ret_type": {".class": "TypeType", "item": "polars.config.Config"}, "type_guard": null, "variables": []}}, "is_overload": false, "var": {".class": "Var", "flags": ["is_initialized_in_class", "is_classmethod", "is_ready"], "fullname": null, "name": "set_fmt_str_lengths", "type": {".class": "CallableType", "arg_kinds": [0, 0], "arg_names": ["cls", "n"], "arg_types": [{".class": "TypeType", "item": "polars.config.Config"}, "builtins.int"], "bound_args": [], "def_extras": {"first_arg": "cls"}, "fallback": "builtins.function", "from_concatenate": false, "implicit": false, "is_ellipsis_args": false, "name": "set_fmt_str_lengths of Config", "ret_type": {".class": "TypeType", "item": "polars.config.Config"}, "type_guard": null, "variables": []}}}}, "set_streaming_chunk_size": {".class": "SymbolTableNode", "kind": "Mdef", "node": {".class": "Decorator", "func": {".class": "FuncDef", "arg_kinds": [0, 0], "arg_names": ["cls", "size"], "flags": ["is_class", "is_decorated"], "fullname": "polars.config.Config.set_streaming_chunk_size", "name": "set_streaming_chunk_size", "type": {".class": "CallableType", "arg_kinds": [0, 0], "arg_names": ["cls", "size"], "arg_types": [{".class": "TypeType", "item": "polars.config.Config"}, "builtins.int"], "bound_args": [], "def_extras": {"first_arg": "cls"}, "fallback": "builtins.function", "from_concatenate": false, "implicit": false, "is_ellipsis_args": false, "name": "set_streaming_chunk_size of Config", "ret_type": {".class": "TypeType", "item": "polars.config.Config"}, "type_guard": null, "variables": []}}, "is_overload": false, "var": {".class": "Var", "flags": ["is_initialized_in_class", "is_classmethod", "is_ready"], "fullname": null, "name": "set_streaming_chunk_size", "type": {".class": "CallableType", "arg_kinds": [0, 0], "arg_names": ["cls", "size"], "arg_types": [{".class": "TypeType", "item": "polars.config.Config"}, "builtins.int"], "bound_args": [], "def_extras": {"first_arg": "cls"}, "fallback": "builtins.function", "from_concatenate": false, "implicit": false, "is_ellipsis_args": false, "name": "set_streaming_chunk_size of Config", "ret_type": {".class": "TypeType", "item": "polars.config.Config"}, "type_guard": null, "variables": []}}}}, "set_tbl_cell_alignment": {".class": "SymbolTableNode", "kind": "Mdef", "node": {".class": "Decorator", "func": {".class": "FuncDef", "arg_kinds": [0, 0], "arg_names": ["cls", "format"], "flags": ["is_class", "is_decorated"], "fullname": "polars.config.Config.set_tbl_cell_alignment", "name": "set_tbl_cell_alignment", "type": {".class": "CallableType", "arg_kinds": [0, 0], "arg_names": ["cls", "format"], "arg_types": [{".class": "TypeType", "item": "polars.config.Config"}, {".class": "UnionType", "items": [{".class": "LiteralType", "fallback": "builtins.str", "value": "LEFT"}, {".class": "LiteralType", "fallback": "builtins.str", "value": "CENTER"}, {".class": "LiteralType", "fallback": "builtins.str", "value": "RIGHT"}]}], "bound_args": [], "def_extras": {"first_arg": "cls"}, "fallback": "builtins.function", "from_concatenate": false, "implicit": false, "is_ellipsis_args": false, "name": "set_tbl_cell_alignment of Config", "ret_type": {".class": "TypeType", "item": "polars.config.Config"}, "type_guard": null, "variables": []}}, "is_overload": false, "var": {".class": "Var", "flags": ["is_initialized_in_class", "is_classmethod", "is_ready"], "fullname": null, "name": "set_tbl_cell_alignment", "type": {".class": "CallableType", "arg_kinds": [0, 0], "arg_names": ["cls", "format"], "arg_types": [{".class": "TypeType", "item": "polars.config.Config"}, {".class": "UnionType", "items": [{".class": "LiteralType", "fallback": "builtins.str", "value": "LEFT"}, {".class": "LiteralType", "fallback": "builtins.str", "value": "CENTER"}, {".class": "LiteralType", "fallback": "builtins.str", "value": "RIGHT"}]}], "bound_args": [], "def_extras": {"first_arg": "cls"}, "fallback": "builtins.function", "from_concatenate": false, "implicit": false, "is_ellipsis_args": false, "name": "set_tbl_cell_alignment of Config", "ret_type": {".class": "TypeType", "item": "polars.config.Config"}, "type_guard": null, "variables": []}}}}, "set_tbl_cols": {".class": "SymbolTableNode", "kind": "Mdef", "node": {".class": "Decorator", "func": {".class": "FuncDef", "arg_kinds": [0, 0], "arg_names": ["cls", "n"], "flags": ["is_class", "is_decorated"], "fullname": "polars.config.Config.set_tbl_cols", "name": "set_tbl_cols", "type": {".class": "CallableType", "arg_kinds": [0, 0], "arg_names": ["cls", "n"], "arg_types": [{".class": "TypeType", "item": "polars.config.Config"}, "builtins.int"], "bound_args": [], "def_extras": {"first_arg": "cls"}, "fallback": "builtins.function", "from_concatenate": false, "implicit": false, "is_ellipsis_args": false, "name": "set_tbl_cols of Config", "ret_type": {".class": "TypeType", "item": "polars.config.Config"}, "type_guard": null, "variables": []}}, "is_overload": false, "var": {".class": "Var", "flags": ["is_initialized_in_class", "is_classmethod", "is_ready"], "fullname": null, "name": "set_tbl_cols", "type": {".class": "CallableType", "arg_kinds": [0, 0], "arg_names": ["cls", "n"], "arg_types": [{".class": "TypeType", "item": "polars.config.Config"}, "builtins.int"], "bound_args": [], "def_extras": {"first_arg": "cls"}, "fallback": "builtins.function", "from_concatenate": false, "implicit": false, "is_ellipsis_args": false, "name": "set_tbl_cols of Config", "ret_type": {".class": "TypeType", "item": "polars.config.Config"}, "type_guard": null, "variables": []}}}}, "set_tbl_column_data_type_inline": {".class": "SymbolTableNode", "kind": "Mdef", "node": {".class": "Decorator", "func": {".class": "FuncDef", "arg_kinds": [0, 1], "arg_names": ["cls", "active"], "flags": ["is_class", "is_decorated"], "fullname": "polars.config.Config.set_tbl_column_data_type_inline", "name": "set_tbl_column_data_type_inline", "type": {".class": "CallableType", "arg_kinds": [0, 1], "arg_names": ["cls", "active"], "arg_types": [{".class": "TypeType", "item": "polars.config.Config"}, "builtins.bool"], "bound_args": [], "def_extras": {"first_arg": "cls"}, "fallback": "builtins.function", "from_concatenate": false, "implicit": false, "is_ellipsis_args": false, "name": "set_tbl_column_data_type_inline of Config", "ret_type": {".class": "TypeType", "item": "polars.config.Config"}, "type_guard": null, "variables": []}}, "is_overload": false, "var": {".class": "Var", "flags": ["is_initialized_in_class", "is_classmethod", "is_ready"], "fullname": null, "name": "set_tbl_column_data_type_inline", "type": {".class": "CallableType", "arg_kinds": [0, 1], "arg_names": ["cls", "active"], "arg_types": [{".class": "TypeType", "item": "polars.config.Config"}, "builtins.bool"], "bound_args": [], "def_extras": {"first_arg": "cls"}, "fallback": "builtins.function", "from_concatenate": false, "implicit": false, "is_ellipsis_args": false, "name": "set_tbl_column_data_type_inline of Config", "ret_type": {".class": "TypeType", "item": "polars.config.Config"}, "type_guard": null, "variables": []}}}}, "set_tbl_dataframe_shape_below": {".class": "SymbolTableNode", "kind": "Mdef", "node": {".class": "Decorator", "func": {".class": "FuncDef", "arg_kinds": [0, 1], "arg_names": ["cls", "active"], "flags": ["is_class", "is_decorated"], "fullname": "polars.config.Config.set_tbl_dataframe_shape_below", "name": "set_tbl_dataframe_shape_below", "type": {".class": "CallableType", "arg_kinds": [0, 1], "arg_names": ["cls", "active"], "arg_types": [{".class": "TypeType", "item": "polars.config.Config"}, "builtins.bool"], "bound_args": [], "def_extras": {"first_arg": "cls"}, "fallback": "builtins.function", "from_concatenate": false, "implicit": false, "is_ellipsis_args": false, "name": "set_tbl_dataframe_shape_below of Config", "ret_type": {".class": "TypeType", "item": "polars.config.Config"}, "type_guard": null, "variables": []}}, "is_overload": false, "var": {".class": "Var", "flags": ["is_initialized_in_class", "is_classmethod", "is_ready"], "fullname": null, "name": "set_tbl_dataframe_shape_below", "type": {".class": "CallableType", "arg_kinds": [0, 1], "arg_names": ["cls", "active"], "arg_types": [{".class": "TypeType", "item": "polars.config.Config"}, "builtins.bool"], "bound_args": [], "def_extras": {"first_arg": "cls"}, "fallback": "builtins.function", "from_concatenate": false, "implicit": false, "is_ellipsis_args": false, "name": "set_tbl_dataframe_shape_below of Config", "ret_type": {".class": "TypeType", "item": "polars.config.Config"}, "type_guard": null, "variables": []}}}}, "set_tbl_formatting": {".class": "SymbolTableNode", "kind": "Mdef", "node": {".class": "Decorator", "func": {".class": "FuncDef", "arg_kinds": [0, 1, 1], "arg_names": ["cls", "format", "rounded_corners"], "flags": ["is_class", "is_decorated"], "fullname": "polars.config.Config.set_tbl_formatting", "name": "set_tbl_formatting", "type": {".class": "CallableType", "arg_kinds": [0, 1, 1], "arg_names": ["cls", "format", "rounded_corners"], "arg_types": [{".class": "TypeType", "item": "polars.config.Config"}, {".class": "UnionType", "items": [{".class": "LiteralType", "fallback": "builtins.str", "value": "ASCII_FULL"}, {".class": "LiteralType", "fallback": "builtins.str", "value": "ASCII_FULL_CONDENSED"}, {".class": "LiteralType", "fallback": "builtins.str", "value": "ASCII_NO_BORDERS"}, {".class": "LiteralType", "fallback": "builtins.str", "value": "ASCII_BORDERS_ONLY"}, {".class": "LiteralType", "fallback": "builtins.str", "value": "ASCII_BORDERS_ONLY_CONDENSED"}, {".class": "LiteralType", "fallback": "builtins.str", "value": "ASCII_HORIZONTAL_ONLY"}, {".class": "LiteralType", "fallback": "builtins.str", "value": "ASCII_MARKDOWN"}, {".class": "LiteralType", "fallback": "builtins.str", "value": "UTF8_FULL"}, {".class": "LiteralType", "fallback": "builtins.str", "value": "UTF8_FULL_CONDENSED"}, {".class": "LiteralType", "fallback": "builtins.str", "value": "UTF8_NO_BORDERS"}, {".class": "LiteralType", "fallback": "builtins.str", "value": "UTF8_BORDERS_ONLY"}, {".class": "LiteralType", "fallback": "builtins.str", "value": "UTF8_HORIZONTAL_ONLY"}, {".class": "LiteralType", "fallback": "builtins.str", "value": "NOTHING"}, {".class": "NoneType"}]}, "builtins.bool"], "bound_args": [], "def_extras": {"first_arg": "cls"}, "fallback": "builtins.function", "from_concatenate": false, "implicit": false, "is_ellipsis_args": false, "name": "set_tbl_formatting of Config", "ret_type": {".class": "TypeType", "item": "polars.config.Config"}, "type_guard": null, "variables": []}}, "is_overload": false, "var": {".class": "Var", "flags": ["is_initialized_in_class", "is_classmethod", "is_ready"], "fullname": null, "name": "set_tbl_formatting", "type": {".class": "CallableType", "arg_kinds": [0, 1, 1], "arg_names": ["cls", "format", "rounded_corners"], "arg_types": [{".class": "TypeType", "item": "polars.config.Config"}, {".class": "UnionType", "items": [{".class": "LiteralType", "fallback": "builtins.str", "value": "ASCII_FULL"}, {".class": "LiteralType", "fallback": "builtins.str", "value": "ASCII_FULL_CONDENSED"}, {".class": "LiteralType", "fallback": "builtins.str", "value": "ASCII_NO_BORDERS"}, {".class": "LiteralType", "fallback": "builtins.str", "value": "ASCII_BORDERS_ONLY"}, {".class": "LiteralType", "fallback": "builtins.str", "value": "ASCII_BORDERS_ONLY_CONDENSED"}, {".class": "LiteralType", "fallback": "builtins.str", "value": "ASCII_HORIZONTAL_ONLY"}, {".class": "LiteralType", "fallback": "builtins.str", "value": "ASCII_MARKDOWN"}, {".class": "LiteralType", "fallback": "builtins.str", "value": "UTF8_FULL"}, {".class": "LiteralType", "fallback": "builtins.str", "value": "UTF8_FULL_CONDENSED"}, {".class": "LiteralType", "fallback": "builtins.str", "value": "UTF8_NO_BORDERS"}, {".class": "LiteralType", "fallback": "builtins.str", "value": "UTF8_BORDERS_ONLY"}, {".class": "LiteralType", "fallback": "builtins.str", "value": "UTF8_HORIZONTAL_ONLY"}, {".class": "LiteralType", "fallback": "builtins.str", "value": "NOTHING"}, {".class": "NoneType"}]}, "builtins.bool"], "bound_args": [], "def_extras": {"first_arg": "cls"}, "fallback": "builtins.function", "from_concatenate": false, "implicit": false, "is_ellipsis_args": false, "name": "set_tbl_formatting of Config", "ret_type": {".class": "TypeType", "item": "polars.config.Config"}, "type_guard": null, "variables": []}}}}, "set_tbl_hide_column_data_types": {".class": "SymbolTableNode", "kind": "Mdef", "node": {".class": "Decorator", "func": {".class": "FuncDef", "arg_kinds": [0, 1], "arg_names": ["cls", "active"], "flags": ["is_class", "is_decorated"], "fullname": "polars.config.Config.set_tbl_hide_column_data_types", "name": "set_tbl_hide_column_data_types", "type": {".class": "CallableType", "arg_kinds": [0, 1], "arg_names": ["cls", "active"], "arg_types": [{".class": "TypeType", "item": "polars.config.Config"}, "builtins.bool"], "bound_args": [], "def_extras": {"first_arg": "cls"}, "fallback": "builtins.function", "from_concatenate": false, "implicit": false, "is_ellipsis_args": false, "name": "set_tbl_hide_column_data_types of Config", "ret_type": {".class": "TypeType", "item": "polars.config.Config"}, "type_guard": null, "variables": []}}, "is_overload": false, "var": {".class": "Var", "flags": ["is_initialized_in_class", "is_classmethod", "is_ready"], "fullname": null, "name": "set_tbl_hide_column_data_types", "type": {".class": "CallableType", "arg_kinds": [0, 1], "arg_names": ["cls", "active"], "arg_types": [{".class": "TypeType", "item": "polars.config.Config"}, "builtins.bool"], "bound_args": [], "def_extras": {"first_arg": "cls"}, "fallback": "builtins.function", "from_concatenate": false, "implicit": false, "is_ellipsis_args": false, "name": "set_tbl_hide_column_data_types of Config", "ret_type": {".class": "TypeType", "item": "polars.config.Config"}, "type_guard": null, "variables": []}}}}, "set_tbl_hide_column_names": {".class": "SymbolTableNode", "kind": "Mdef", "node": {".class": "Decorator", "func": {".class": "FuncDef", "arg_kinds": [0, 1], "arg_names": ["cls", "active"], "flags": ["is_class", "is_decorated"], "fullname": "polars.config.Config.set_tbl_hide_column_names", "name": "set_tbl_hide_column_names", "type": {".class": "CallableType", "arg_kinds": [0, 1], "arg_names": ["cls", "active"], "arg_types": [{".class": "TypeType", "item": "polars.config.Config"}, "builtins.bool"], "bound_args": [], "def_extras": {"first_arg": "cls"}, "fallback": "builtins.function", "from_concatenate": false, "implicit": false, "is_ellipsis_args": false, "name": "set_tbl_hide_column_names of Config", "ret_type": {".class": "TypeType", "item": "polars.config.Config"}, "type_guard": null, "variables": []}}, "is_overload": false, "var": {".class": "Var", "flags": ["is_initialized_in_class", "is_classmethod", "is_ready"], "fullname": null, "name": "set_tbl_hide_column_names", "type": {".class": "CallableType", "arg_kinds": [0, 1], "arg_names": ["cls", "active"], "arg_types": [{".class": "TypeType", "item": "polars.config.Config"}, "builtins.bool"], "bound_args": [], "def_extras": {"first_arg": "cls"}, "fallback": "builtins.function", "from_concatenate": false, "implicit": false, "is_ellipsis_args": false, "name": "set_tbl_hide_column_names of Config", "ret_type": {".class": "TypeType", "item": "polars.config.Config"}, "type_guard": null, "variables": []}}}}, "set_tbl_hide_dataframe_shape": {".class": "SymbolTableNode", "kind": "Mdef", "node": {".class": "Decorator", "func": {".class": "FuncDef", "arg_kinds": [0, 1], "arg_names": ["cls", "active"], "flags": ["is_class", "is_decorated"], "fullname": "polars.config.Config.set_tbl_hide_dataframe_shape", "name": "set_tbl_hide_dataframe_shape", "type": {".class": "CallableType", "arg_kinds": [0, 1], "arg_names": ["cls", "active"], "arg_types": [{".class": "TypeType", "item": "polars.config.Config"}, "builtins.bool"], "bound_args": [], "def_extras": {"first_arg": "cls"}, "fallback": "builtins.function", "from_concatenate": false, "implicit": false, "is_ellipsis_args": false, "name": "set_tbl_hide_dataframe_shape of Config", "ret_type": {".class": "TypeType", "item": "polars.config.Config"}, "type_guard": null, "variables": []}}, "is_overload": false, "var": {".class": "Var", "flags": ["is_initialized_in_class", "is_classmethod", "is_ready"], "fullname": null, "name": "set_tbl_hide_dataframe_shape", "type": {".class": "CallableType", "arg_kinds": [0, 1], "arg_names": ["cls", "active"], "arg_types": [{".class": "TypeType", "item": "polars.config.Config"}, "builtins.bool"], "bound_args": [], "def_extras": {"first_arg": "cls"}, "fallback": "builtins.function", "from_concatenate": false, "implicit": false, "is_ellipsis_args": false, "name": "set_tbl_hide_dataframe_shape of Config", "ret_type": {".class": "TypeType", "item": "polars.config.Config"}, "type_guard": null, "variables": []}}}}, "set_tbl_hide_dtype_separator": {".class": "SymbolTableNode", "kind": "Mdef", "node": {".class": "Decorator", "func": {".class": "FuncDef", "arg_kinds": [0, 1], "arg_names": ["cls", "active"], "flags": ["is_class", "is_decorated"], "fullname": "polars.config.Config.set_tbl_hide_dtype_separator", "name": "set_tbl_hide_dtype_separator", "type": {".class": "CallableType", "arg_kinds": [0, 1], "arg_names": ["cls", "active"], "arg_types": [{".class": "TypeType", "item": "polars.config.Config"}, "builtins.bool"], "bound_args": [], "def_extras": {"first_arg": "cls"}, "fallback": "builtins.function", "from_concatenate": false, "implicit": false, "is_ellipsis_args": false, "name": "set_tbl_hide_dtype_separator of Config", "ret_type": {".class": "TypeType", "item": "polars.config.Config"}, "type_guard": null, "variables": []}}, "is_overload": false, "var": {".class": "Var", "flags": ["is_initialized_in_class", "is_classmethod", "is_ready"], "fullname": null, "name": "set_tbl_hide_dtype_separator", "type": {".class": "CallableType", "arg_kinds": [0, 1], "arg_names": ["cls", "active"], "arg_types": [{".class": "TypeType", "item": "polars.config.Config"}, "builtins.bool"], "bound_args": [], "def_extras": {"first_arg": "cls"}, "fallback": "builtins.function", "from_concatenate": false, "implicit": false, "is_ellipsis_args": false, "name": "set_tbl_hide_dtype_separator of Config", "ret_type": {".class": "TypeType", "item": "polars.config.Config"}, "type_guard": null, "variables": []}}}}, "set_tbl_rows": {".class": "SymbolTableNode", "kind": "Mdef", "node": {".class": "Decorator", "func": {".class": "FuncDef", "arg_kinds": [0, 0], "arg_names": ["cls", "n"], "flags": ["is_class", "is_decorated"], "fullname": "polars.config.Config.set_tbl_rows", "name": "set_tbl_rows", "type": {".class": "CallableType", "arg_kinds": [0, 0], "arg_names": ["cls", "n"], "arg_types": [{".class": "TypeType", "item": "polars.config.Config"}, "builtins.int"], "bound_args": [], "def_extras": {"first_arg": "cls"}, "fallback": "builtins.function", "from_concatenate": false, "implicit": false, "is_ellipsis_args": false, "name": "set_tbl_rows of Config", "ret_type": {".class": "TypeType", "item": "polars.config.Config"}, "type_guard": null, "variables": []}}, "is_overload": false, "var": {".class": "Var", "flags": ["is_initialized_in_class", "is_classmethod", "is_ready"], "fullname": null, "name": "set_tbl_rows", "type": {".class": "CallableType", "arg_kinds": [0, 0], "arg_names": ["cls", "n"], "arg_types": [{".class": "TypeType", "item": "polars.config.Config"}, "builtins.int"], "bound_args": [], "def_extras": {"first_arg": "cls"}, "fallback": "builtins.function", "from_concatenate": false, "implicit": false, "is_ellipsis_args": false, "name": "set_tbl_rows of Config", "ret_type": {".class": "TypeType", "item": "polars.config.Config"}, "type_guard": null, "variables": []}}}}, "set_tbl_width_chars": {".class": "SymbolTableNode", "kind": "Mdef", "node": {".class": "Decorator", "func": {".class": "FuncDef", "arg_kinds": [0, 0], "arg_names": ["cls", "width"], "flags": ["is_class", "is_decorated"], "fullname": "polars.config.Config.set_tbl_width_chars", "name": "set_tbl_width_chars", "type": {".class": "CallableType", "arg_kinds": [0, 0], "arg_names": ["cls", "width"], "arg_types": [{".class": "TypeType", "item": "polars.config.Config"}, "builtins.int"], "bound_args": [], "def_extras": {"first_arg": "cls"}, "fallback": "builtins.function", "from_concatenate": false, "implicit": false, "is_ellipsis_args": false, "name": "set_tbl_width_chars of Config", "ret_type": {".class": "TypeType", "item": "polars.config.Config"}, "type_guard": null, "variables": []}}, "is_overload": false, "var": {".class": "Var", "flags": ["is_initialized_in_class", "is_classmethod", "is_ready"], "fullname": null, "name": "set_tbl_width_chars", "type": {".class": "CallableType", "arg_kinds": [0, 0], "arg_names": ["cls", "width"], "arg_types": [{".class": "TypeType", "item": "polars.config.Config"}, "builtins.int"], "bound_args": [], "def_extras": {"first_arg": "cls"}, "fallback": "builtins.function", "from_concatenate": false, "implicit": false, "is_ellipsis_args": false, "name": "set_tbl_width_chars of Config", "ret_type": {".class": "TypeType", "item": "polars.config.Config"}, "type_guard": null, "variables": []}}}}, "set_verbose": {".class": "SymbolTableNode", "kind": "Mdef", "node": {".class": "Decorator", "func": {".class": "FuncDef", "arg_kinds": [0, 1], "arg_names": ["cls", "active"], "flags": ["is_class", "is_decorated"], "fullname": "polars.config.Config.set_verbose", "name": "set_verbose", "type": {".class": "CallableType", "arg_kinds": [0, 1], "arg_names": ["cls", "active"], "arg_types": [{".class": "TypeType", "item": "polars.config.Config"}, "builtins.bool"], "bound_args": [], "def_extras": {"first_arg": "cls"}, "fallback": "builtins.function", "from_concatenate": false, "implicit": false, "is_ellipsis_args": false, "name": "set_verbose of Config", "ret_type": {".class": "TypeType", "item": "polars.config.Config"}, "type_guard": null, "variables": []}}, "is_overload": false, "var": {".class": "Var", "flags": ["is_initialized_in_class", "is_classmethod", "is_ready"], "fullname": null, "name": "set_verbose", "type": {".class": "CallableType", "arg_kinds": [0, 1], "arg_names": ["cls", "active"], "arg_types": [{".class": "TypeType", "item": "polars.config.Config"}, "builtins.bool"], "bound_args": [], "def_extras": {"first_arg": "cls"}, "fallback": "builtins.function", "from_concatenate": false, "implicit": false, "is_ellipsis_args": false, "name": "set_verbose of Config", "ret_type": {".class": "TypeType", "item": "polars.config.Config"}, "type_guard": null, "variables": []}}}}, "state": {".class": "SymbolTableNode", "kind": "Mdef", "node": {".class": "Decorator", "func": {".class": "FuncDef", "arg_kinds": [0, 1, 1], "arg_names": ["cls", "if_set", "env_only"], "flags": ["is_class", "is_decorated"], "fullname": "polars.config.Config.state", "name": "state", "type": {".class": "CallableType", "arg_kinds": [0, 1, 1], "arg_names": ["cls", "if_set", "env_only"], "arg_types": [{".class": "TypeType", "item": "polars.config.Config"}, "builtins.bool", "builtins.bool"], "bound_args": [], "def_extras": {"first_arg": "cls"}, "fallback": "builtins.function", "from_concatenate": false, "implicit": false, "is_ellipsis_args": false, "name": "state of Config", "ret_type": {".class": "Instance", "args": ["builtins.str", {".class": "UnionType", "items": ["builtins.str", {".class": "NoneType"}]}], "type_ref": "builtins.dict"}, "type_guard": null, "variables": []}}, "is_overload": false, "var": {".class": "Var", "flags": ["is_initialized_in_class", "is_classmethod", "is_ready"], "fullname": null, "name": "state", "type": {".class": "CallableType", "arg_kinds": [0, 1, 1], "arg_names": ["cls", "if_set", "env_only"], "arg_types": [{".class": "TypeType", "item": "polars.config.Config"}, "builtins.bool", "builtins.bool"], "bound_args": [], "def_extras": {"first_arg": "cls"}, "fallback": "builtins.function", "from_concatenate": false, "implicit": false, "is_ellipsis_args": false, "name": "state of Config", "ret_type": {".class": "Instance", "args": ["builtins.str", {".class": "UnionType", "items": ["builtins.str", {".class": "NoneType"}]}], "type_ref": "builtins.dict"}, "type_guard": null, "variables": []}}}}}, "slots": null, "tuple_type": null, "type_vars": [], "typeddict_type": null}}, "FloatFmt": {".class": "SymbolTableNode", "cross_ref": "polars.type_aliases.FloatFmt", "kind": "Gdef"}, "Literal": {".class": "SymbolTableNode", "cross_ref": "typing.Literal", "kind": "Gdef"}, "TYPE_CHECKING": {".class": "SymbolTableNode", "cross_ref": "typing.TYPE_CHECKING", "kind": "Gdef"}, "TracebackType": {".class": "SymbolTableNode", "cross_ref": "types.TracebackType", "kind": "Gdef"}, "_POLARS_CFG_DIRECT_VARS": {".class": "SymbolTableNode", "kind": "Gdef", "node": {".class": "Var", "flags": ["has_explicit_value"], "fullname": "polars.config._POLARS_CFG_DIRECT_VARS", "name": "_POLARS_CFG_DIRECT_VARS", "type": {".class": "Instance", "args": ["builtins.str", {".class": "CallableType", "arg_kinds": [], "arg_names": [], "arg_types": [], "bound_args": [], "def_extras": {"first_arg": null}, "fallback": "builtins.function", "from_concatenate": false, "implicit": false, "is_ellipsis_args": false, "name": "_get_float_fmt", "ret_type": "builtins.str", "type_guard": null, "variables": []}], "type_ref": "builtins.dict"}}}, "_POLARS_CFG_ENV_VARS": {".class": "SymbolTableNode", "kind": "Gdef", "node": {".class": "Var", "flags": ["has_explicit_value"], "fullname": "polars.config._POLARS_CFG_ENV_VARS", "name": "_POLARS_CFG_ENV_VARS", "type": {".class": "Instance", "args": ["builtins.str"], "type_ref": "builtins.set"}}}, "__annotations__": {".class": "SymbolTableNode", "kind": "Gdef", "node": {".class": "Var", "flags": ["is_ready"], "fullname": "polars.config.__annotations__", "name": "__annotations__", "type": {".class": "Instance", "args": ["builtins.str", {".class": "AnyType", "missing_import_name": null, "source_any": null, "type_of_any": 6}], "type_ref": "builtins.dict"}}}, "__doc__": {".class": "SymbolTableNode", "kind": "Gdef", "node": {".class": "Var", "flags": ["is_ready"], "fullname": "polars.config.__doc__", "name": "__doc__", "type": "builtins.str"}}, "__file__": {".class": "SymbolTableNode", "kind": "Gdef", "node": {".class": "Var", "flags": ["is_ready"], "fullname": "polars.config.__file__", "name": "__file__", "type": "builtins.str"}}, "__name__": {".class": "SymbolTableNode", "kind": "Gdef", "node": {".class": "Var", "flags": ["is_ready"], "fullname": "polars.config.__name__", "name": "__name__", "type": "builtins.str"}}, "__package__": {".class": "SymbolTableNode", "kind": "Gdef", "node": {".class": "Var", "flags": ["is_ready"], "fullname": "polars.config.__package__", "name": "__package__", "type": "builtins.str"}}, "_get_float_fmt": {".class": "SymbolTableNode", "kind": "Gdef", "node": {".class": "FuncDef", "arg_kinds": [], "arg_names": [], "flags": [], "fullname": "polars.config._get_float_fmt", "name": "_get_float_fmt", "type": {".class": "CallableType", "arg_kinds": [], "arg_names": [], "arg_types": [], "bound_args": [], "def_extras": {"first_arg": null}, "fallback": "builtins.function", "from_concatenate": false, "implicit": false, "is_ellipsis_args": false, "name": "_get_float_fmt", "ret_type": "builtins.str", "type_guard": null, "variables": []}}}, "_set_float_fmt": {".class": "SymbolTableNode", "kind": "Gdef", "node": {".class": "Var", "flags": ["is_suppressed_import", "is_ready"], "fullname": "polars.config._set_float_fmt", "name": "_set_float_fmt", "type": {".class": "AnyType", "missing_import_name": "polars.config._set_float_fmt", "source_any": null, "type_of_any": 3}}}, "annotations": {".class": "SymbolTableNode", "cross_ref": "__future__.annotations", "kind": "Gdef"}, "contextlib": {".class": "SymbolTableNode", "cross_ref": "contextlib", "kind": "Gdef"}, "json": {".class": "SymbolTableNode", "cross_ref": "json", "kind": "Gdef"}, "os": {".class": "SymbolTableNode", "cross_ref": "os", "kind": "Gdef"}, "sys": {".class": "SymbolTableNode", "cross_ref": "sys", "kind": "Gdef"}}, "path": "/cellar/users/dlaub/miniconda3/envs/drugcell_transfer/lib/python3.9/site-packages/polars/config.py"}