{".class": "MypyFile", "_fullname": "hypothesis.strategies._internal.misc", "future_import_flags": [], "is_partial_stub_package": false, "is_stub": false, "names": {".class": "SymbolTable", "JustStrategy": {".class": "SymbolTableNode", "kind": "Gdef", "node": {".class": "TypeInfo", "_promote": null, "abstract_attributes": [], "bases": ["hypothesis.strategies._internal.strategies.SampledFromStrategy"], "declared_metaclass": null, "defn": {".class": "ClassDef", "fullname": "hypothesis.strategies._internal.misc.JustStrategy", "name": "JustStrategy", "type_vars": []}, "deletable_attributes": [], "flags": [], "fullname": "hypothesis.strategies._internal.misc.JustStrategy", "has_param_spec_type": false, "metaclass_type": null, "metadata": {}, "module_name": "hypothesis.strategies._internal.misc", "mro": ["hypothesis.strategies._internal.misc.JustStrategy", "hypothesis.strategies._internal.strategies.SampledFromStrategy", "hypothesis.strategies._internal.strategies.SearchStrategy", "builtins.object"], "names": {".class": "SymbolTable", "__repr__": {".class": "SymbolTableNode", "kind": "Mdef", "node": {".class": "FuncDef", "arg_kinds": [0], "arg_names": [null], "flags": [], "fullname": "hypothesis.strategies._internal.misc.JustStrategy.__repr__", "name": "__repr__", "type": null}}, "calc_is_cacheable": {".class": "SymbolTableNode", "kind": "Mdef", "node": {".class": "FuncDef", "arg_kinds": [0, 0], "arg_names": ["self", "recur"], "flags": [], "fullname": "hypothesis.strategies._internal.misc.JustStrategy.calc_is_cacheable", "name": "calc_is_cacheable", "type": null}}, "do_filtered_draw": {".class": "SymbolTableNode", "kind": "Mdef", "node": {".class": "FuncDef", "arg_kinds": [0, 0], "arg_names": ["self", "data"], "flags": [], "fullname": "hypothesis.strategies._internal.misc.JustStrategy.do_filtered_draw", "name": "do_filtered_draw", "type": null}}, "value": {".class": "SymbolTableNode", "kind": "Mdef", "node": {".class": "Decorator", "func": {".class": "FuncDef", "arg_kinds": [0], "arg_names": ["self"], "flags": ["is_property", "is_decorated"], "fullname": "hypothesis.strategies._internal.misc.JustStrategy.value", "name": "value", "type": null}, "is_overload": false, "var": {".class": "Var", "flags": ["is_initialized_in_class", "is_property", "is_ready"], "fullname": null, "name": "value", "type": {".class": "CallableType", "arg_kinds": [0], "arg_names": ["self"], "arg_types": ["hypothesis.strategies._internal.misc.JustStrategy"], "bound_args": [], "def_extras": {"first_arg": "self"}, "fallback": "builtins.function", "from_concatenate": false, "implicit": true, "is_ellipsis_args": false, "name": "value of JustStrategy", "ret_type": {".class": "AnyType", "missing_import_name": null, "source_any": null, "type_of_any": 1}, "type_guard": null, "variables": []}}}}}, "slots": null, "tuple_type": null, "type_vars": [], "typeddict_type": null}}, "NOTHING": {".class": "SymbolTableNode", "kind": "Gdef", "node": {".class": "Var", "flags": ["has_explicit_value"], "fullname": "hypothesis.strategies._internal.misc.NOTHING", "name": "NOTHING", "type": "hypothesis.strategies._internal.misc.Nothing"}}, "Nothing": {".class": "SymbolTableNode", "kind": "Gdef", "node": {".class": "TypeInfo", "_promote": null, "abstract_attributes": [], "bases": [{".class": "Instance", "args": [{".class": "AnyType", "missing_import_name": null, "source_any": null, "type_of_any": 4}], "type_ref": "hypothesis.strategies._internal.strategies.SearchStrategy"}], "declared_metaclass": null, "defn": {".class": "ClassDef", "fullname": "hypothesis.strategies._internal.misc.Nothing", "name": "Nothing", "type_vars": []}, "deletable_attributes": [], "flags": [], "fullname": "hypothesis.strategies._internal.misc.Nothing", "has_param_spec_type": false, "metaclass_type": null, "metadata": {}, "module_name": "hypothesis.strategies._internal.misc", "mro": ["hypothesis.strategies._internal.misc.Nothing", "hypothesis.strategies._internal.strategies.SearchStrategy", "builtins.object"], "names": {".class": "SymbolTable", "__repr__": {".class": "SymbolTableNode", "kind": "Mdef", "node": {".class": "FuncDef", "arg_kinds": [0], "arg_names": [null], "flags": [], "fullname": "hypothesis.strategies._internal.misc.Nothing.__repr__", "name": "__repr__", "type": null}}, "calc_has_reusable_values": {".class": "SymbolTableNode", "kind": "Mdef", "node": {".class": "FuncDef", "arg_kinds": [0, 0], "arg_names": ["self", "recur"], "flags": [], "fullname": "hypothesis.strategies._internal.misc.Nothing.calc_has_reusable_values", "name": "calc_has_reusable_values", "type": null}}, "calc_is_empty": {".class": "SymbolTableNode", "kind": "Mdef", "node": {".class": "FuncDef", "arg_kinds": [0, 0], "arg_names": ["self", "recur"], "flags": [], "fullname": "hypothesis.strategies._internal.misc.Nothing.calc_is_empty", "name": "calc_is_empty", "type": null}}, "do_draw": {".class": "SymbolTableNode", "kind": "Mdef", "node": {".class": "FuncDef", "arg_kinds": [0, 0], "arg_names": ["self", "data"], "flags": [], "fullname": "hypothesis.strategies._internal.misc.Nothing.do_draw", "name": "do_draw", "type": null}}, "filter": {".class": "SymbolTableNode", "kind": "Mdef", "node": {".class": "FuncDef", "arg_kinds": [0, 0], "arg_names": ["self", "f"], "flags": [], "fullname": "hypothesis.strategies._internal.misc.Nothing.filter", "name": "filter", "type": null}}, "flatmap": {".class": "SymbolTableNode", "kind": "Mdef", "node": {".class": "FuncDef", "arg_kinds": [0, 0], "arg_names": ["self", "f"], "flags": [], "fullname": "hypothesis.strategies._internal.misc.Nothing.flatmap", "name": "flatmap", "type": null}}, "map": {".class": "SymbolTableNode", "kind": "Mdef", "node": {".class": "FuncDef", "arg_kinds": [0, 0], "arg_names": ["self", "f"], "flags": [], "fullname": "hypothesis.strategies._internal.misc.Nothing.map", "name": "map", "type": null}}}, "slots": null, "tuple_type": null, "type_vars": [], "typeddict_type": null}}, "SampledFromStrategy": {".class": "SymbolTableNode", "cross_ref": "hypothesis.strategies._internal.strategies.SampledFromStrategy", "kind": "Gdef"}, "SearchStrategy": {".class": "SymbolTableNode", "cross_ref": "hypothesis.strategies._internal.strategies.SearchStrategy", "kind": "Gdef"}, "T": {".class": "SymbolTableNode", "cross_ref": "hypothesis.strategies._internal.strategies.T", "kind": "Gdef"}, "__annotations__": {".class": "SymbolTableNode", "kind": "Gdef", "node": {".class": "Var", "flags": ["is_ready"], "fullname": "hypothesis.strategies._internal.misc.__annotations__", "name": "__annotations__", "type": {".class": "Instance", "args": ["builtins.str", {".class": "AnyType", "missing_import_name": null, "source_any": null, "type_of_any": 6}], "type_ref": "builtins.dict"}}}, "__doc__": {".class": "SymbolTableNode", "kind": "Gdef", "node": {".class": "Var", "flags": ["is_ready"], "fullname": "hypothesis.strategies._internal.misc.__doc__", "name": "__doc__", "type": "builtins.str"}}, "__file__": {".class": "SymbolTableNode", "kind": "Gdef", "node": {".class": "Var", "flags": ["is_ready"], "fullname": "hypothesis.strategies._internal.misc.__file__", "name": "__file__", "type": "builtins.str"}}, "__name__": {".class": "SymbolTableNode", "kind": "Gdef", "node": {".class": "Var", "flags": ["is_ready"], "fullname": "hypothesis.strategies._internal.misc.__name__", "name": "__name__", "type": "builtins.str"}}, "__package__": {".class": "SymbolTableNode", "kind": "Gdef", "node": {".class": "Var", "flags": ["is_ready"], "fullname": "hypothesis.strategies._internal.misc.__package__", "name": "__package__", "type": "builtins.str"}}, "cacheable": {".class": "SymbolTableNode", "cross_ref": "hypothesis.strategies._internal.utils.cacheable", "kind": "Gdef"}, "defines_strategy": {".class": "SymbolTableNode", "cross_ref": "hypothesis.strategies._internal.utils.defines_strategy", "kind": "Gdef"}, "get_pretty_function_description": {".class": "SymbolTableNode", "cross_ref": "hypothesis.internal.reflection.get_pretty_function_description", "kind": "Gdef"}, "is_simple_data": {".class": "SymbolTableNode", "cross_ref": "hypothesis.strategies._internal.strategies.is_simple_data", "kind": "Gdef"}, "just": {".class": "SymbolTableNode", "kind": "Gdef", "node": {".class": "Decorator", "func": {".class": "FuncDef", "arg_kinds": [0], "arg_names": ["value"], "flags": ["is_decorated"], "fullname": "hypothesis.strategies._internal.misc.just", "name": "just", "type": {".class": "CallableType", "arg_kinds": [0], "arg_names": ["value"], "arg_types": [{".class": "TypeVarType", "fullname": "hypothesis.strategies._internal.strategies.T", "id": -1, "name": "T", "namespace": "", "upper_bound": "builtins.object", "values": [], "variance": 0}], "bound_args": [], "def_extras": {"first_arg": null}, "fallback": "builtins.function", "from_concatenate": false, "implicit": false, "is_ellipsis_args": false, "name": "just", "ret_type": {".class": "Instance", "args": [{".class": "TypeVarType", "fullname": "hypothesis.strategies._internal.strategies.T", "id": -1, "name": "T", "namespace": "", "upper_bound": "builtins.object", "values": [], "variance": 0}], "type_ref": "hypothesis.strategies._internal.strategies.SearchStrategy"}, "type_guard": null, "variables": [{".class": "TypeVarType", "fullname": "hypothesis.strategies._internal.strategies.T", "id": -1, "name": "T", "namespace": "", "upper_bound": "builtins.object", "values": [], "variance": 0}]}}, "is_overload": false, "var": {".class": "Var", "flags": ["is_ready"], "fullname": null, "name": "just", "type": {".class": "CallableType", "arg_kinds": [0], "arg_names": ["value"], "arg_types": [{".class": "TypeVarType", "fullname": "hypothesis.strategies._internal.strategies.T", "id": -1, "name": "T", "namespace": "", "upper_bound": "builtins.object", "values": [], "variance": 0}], "bound_args": [], "def_extras": {"first_arg": null}, "fallback": "builtins.function", "from_concatenate": false, "implicit": false, "is_ellipsis_args": false, "name": "just", "ret_type": {".class": "Instance", "args": [{".class": "TypeVarType", "fullname": "hypothesis.strategies._internal.strategies.T", "id": -1, "name": "T", "namespace": "", "upper_bound": "builtins.object", "values": [], "variance": 0}], "type_ref": "hypothesis.strategies._internal.strategies.SearchStrategy"}, "type_guard": null, "variables": [{".class": "TypeVarType", "fullname": "hypothesis.strategies._internal.strategies.T", "id": -1, "name": "T", "namespace": "", "upper_bound": "builtins.object", "values": [], "variance": 0}]}}}}, "none": {".class": "SymbolTableNode", "kind": "Gdef", "node": {".class": "Decorator", "func": {".class": "FuncDef", "arg_kinds": [], "arg_names": [], "flags": ["is_decorated"], "fullname": "hypothesis.strategies._internal.misc.none", "name": "none", "type": {".class": "CallableType", "arg_kinds": [], "arg_names": [], "arg_types": [], "bound_args": [], "def_extras": {"first_arg": null}, "fallback": "builtins.function", "from_concatenate": false, "implicit": false, "is_ellipsis_args": false, "name": "none", "ret_type": {".class": "Instance", "args": [{".class": "NoneType"}], "type_ref": "hypothesis.strategies._internal.strategies.SearchStrategy"}, "type_guard": null, "variables": []}}, "is_overload": false, "var": {".class": "Var", "flags": ["is_ready"], "fullname": null, "name": "none", "type": {".class": "CallableType", "arg_kinds": [], "arg_names": [], "arg_types": [], "bound_args": [], "def_extras": {"first_arg": null}, "fallback": "builtins.function", "from_concatenate": false, "implicit": false, "is_ellipsis_args": false, "name": "none", "ret_type": {".class": "Instance", "args": [{".class": "NoneType"}], "type_ref": "hypothesis.strategies._internal.strategies.SearchStrategy"}, "type_guard": null, "variables": []}}}}, "nothing": {".class": "SymbolTableNode", "kind": "Gdef", "node": {".class": "Decorator", "func": {".class": "FuncDef", "arg_kinds": [], "arg_names": [], "flags": ["is_decorated"], "fullname": "hypothesis.strategies._internal.misc.nothing", "name": "nothing", "type": {".class": "CallableType", "arg_kinds": [], "arg_names": [], "arg_types": [], "bound_args": [], "def_extras": {"first_arg": null}, "fallback": "builtins.function", "from_concatenate": false, "implicit": false, "is_ellipsis_args": false, "name": "nothing", "ret_type": {".class": "Instance", "args": [{".class": "AnyType", "missing_import_name": null, "source_any": null, "type_of_any": 4}], "type_ref": "hypothesis.strategies._internal.strategies.SearchStrategy"}, "type_guard": null, "variables": []}}, "is_overload": false, "var": {".class": "Var", "flags": ["is_ready"], "fullname": null, "name": "nothing", "type": {".class": "CallableType", "arg_kinds": [], "arg_names": [], "arg_types": [], "bound_args": [], "def_extras": {"first_arg": null}, "fallback": "builtins.function", "from_concatenate": false, "implicit": false, "is_ellipsis_args": false, "name": "nothing", "ret_type": {".class": "Instance", "args": [{".class": "AnyType", "missing_import_name": null, "source_any": null, "type_of_any": 4}], "type_ref": "hypothesis.strategies._internal.strategies.SearchStrategy"}, "type_guard": null, "variables": []}}}}}, "path": "/cellar/users/dlaub/miniconda3/envs/drugcell_transfer/lib/python3.9/site-packages/hypothesis/strategies/_internal/misc.py"}